01_combinational_circuits/04_mux/04_8-1mux/8_1mux.v
module mux8_1(a, sel, y); 
     input [7:0] a;
     input [2:0] sel;
     output reg y;
     always @(*) begin
        case(sel)
            3'b000 : y = a[0];
            3'b001 : y = a[1];
            3'b010 : y = a[2];
            3'b011 : y = a[3];
            3'b100 : y = a[4];
            3'b101 : y = a[5];
            3'b110 : y = a[6];
            3'b111 : y = a[7];
        endcase
     end
endmodule

01_combinational_circuits/04_mux/04_8-1mux/8_1mux_tb.v
module mux8_tb;

    reg [7:0] a;
    reg [2:0] sel;
    wire y;

    mux8_1 uut(a, sel, y);

    integer i, j;

    initial begin
        $monitor("a=%b sel=%b -> y=%b", a, sel, y);

        $dumpfile("mux8_tb.vcd");
        $dumpvars(0, mux8_tb);

        for(i = 0; i < 256; i = i + 1) begin
            a = i;
            for(j = 0; j < 8; j = j + 1) begin
                sel = j;
                #10;
            end
        end

        $finish;
    end

endmodule

01_combinational_circuits/04_mux/04_8-1mux/mux8_tb.vcd
$date
	Wed Apr 22 16:17:33 2026
$end
$version
	Icarus Verilog
$end
$timescale
	1s
$end
$scope module mux8_tb $end
$var wire 1 ! y $end
$var reg 8 " a [7:0] $end
$var integer 32 # i [31:0] $end
$var integer 32 $ j [31:0] $end
$var reg 3 % sel [2:0] $end
$scope module uut $end
$var wire 8 & a [7:0] $end
$var wire 3 ' sel [2:0] $end
$var reg 1 ( y $end
$upscope $end
$upscope $end
$enddefinitions $end
#0
$dumpvars
0(
b0 '
b0 &
b0 %
b0 $
b0 #
b0 "
0!
$end
#10
b1 %
b1 '
b1 $
#20
b10 %
b10 '
b10 $
#30
b11 %
b11 '
b11 $
#40
b100 %
b100 '
b100 $
#50
b101 %
b101 '
b101 $
#60
b110 %
b110 '
b110 $
#70
b111 %
b111 '
b111 $
#80
1(
1!
b0 %
b0 '
b1 "
b1 &
b1 #
b0 $
#90
0(
0!
b1 %
b1 '
b1 $
#100
b10 %
b10 '
b10 $
#110
b11 %
b11 '
b11 $
#120
b100 %
b100 '
b100 $
#130
b101 %
b101 '
b101 $
#140
b110 %
b110 '
b110 $
#150
b111 %
b111 '
b111 $
#160
b0 %
b0 '
b10 "
b10 &
b10 #
b0 $
#170
1(
1!
b1 %
b1 '
b1 $
#180
0(
0!
b10 %
b10 '
b10 $
#190
b11 %
b11 '
b11 $
#200
b100 %
b100 '
b100 $
#210
b101 %
b101 '
b101 $
#220
b110 %
b110 '
b110 $
#230
b111 %
b111 '
b111 $
#240
1(
1!
b0 %
b0 '
b11 "
b11 &
b11 #
b0 $
#250
b1 %
b1 '
b1 $
#260
0(
0!
b10 %
b10 '
b10 $
#270
b11 %
b11 '
b11 $
#280
b100 %
b100 '
b100 $
#290
b101 %
b101 '
b101 $
#300
b110 %
b110 '
b110 $
#310
b111 %
b111 '
b111 $
#320
b0 %
b0 '
b100 "
b100 &
b100 #
b0 $
#330
b1 %
b1 '
b1 $
#340
1(
1!
b10 %
b10 '
b10 $
#350
0(
0!
b11 %
b11 '
b11 $
#360
b100 %
b100 '
b100 $
#370
b101 %
b101 '
b101 $
#380
b110 %
b110 '
b110 $
#390
b111 %
b111 '
b111 $
#400
1(
1!
b0 %
b0 '
b101 "
b101 &
b101 #
b0 $
#410
0(
0!
b1 %
b1 '
b1 $
#420
1(
1!
b10 %
b10 '
b10 $
#430
0(
0!
b11 %
b11 '
b11 $
#440
b100 %
b100 '
b100 $
#450
b101 %
b101 '
b101 $
#460
b110 %
b110 '
b110 $
#470
b111 %
b111 '
b111 $
#480
b0 %
b0 '
b110 "
b110 &
b110 #
b0 $
#490
1(
1!
b1 %
b1 '
b1 $
#500
b10 %
b10 '
b10 $
#510
0(
0!
b11 %
b11 '
b11 $
#520
b100 %
b100 '
b100 $
#530
b101 %
b101 '
b101 $
#540
b110 %
b110 '
b110 $
#550
b111 %
b111 '
b111 $
#560
1(
1!
b0 %
b0 '
b111 "
b111 &
b111 #
b0 $
#570
b1 %
b1 '
b1 $
#580
b10 %
b10 '
b10 $
#590
0(
0!
b11 %
b11 '
b11 $
#600
b100 %
b100 '
b100 $
#610
b101 %
b101 '
b101 $
#620
b110 %
b110 '
b110 $
#630
b111 %
b111 '
b111 $
#640
b0 %
b0 '
b1000 "
b1000 &
b1000 #
b0 $
#650
b1 %
b1 '
b1 $
#660
b10 %
b10 '
b10 $
#670
1(
1!
b11 %
b11 '
b11 $
#680
0(
0!
b100 %
b100 '
b100 $
#690
b101 %
b101 '
b101 $
#700
b110 %
b110 '
b110 $
#710
b111 %
b111 '
b111 $
#720
1(
1!
b0 %
b0 '
b1001 "
b1001 &
b1001 #
b0 $
#730
0(
0!
b1 %
b1 '
b1 $
#740
b10 %
b10 '
b10 $
#750
1(
1!
b11 %
b11 '
b11 $
#760
0(
0!
b100 %
b100 '
b100 $
#770
b101 %
b101 '
b101 $
#780
b110 %
b110 '
b110 $
#790
b111 %
b111 '
b111 $
#800
b0 %
b0 '
b1010 "
b1010 &
b1010 #
b0 $
#810
1(
1!
b1 %
b1 '
b1 $
#820
0(
0!
b10 %
b10 '
b10 $
#830
1(
1!
b11 %
b11 '
b11 $
#840
0(
0!
b100 %
b100 '
b100 $
#850
b101 %
b101 '
b101 $
#860
b110 %
b110 '
b110 $
#870
b111 %
b111 '
b111 $
#880
1(
1!
b0 %
b0 '
b1011 "
b1011 &
b1011 #
b0 $
#890
b1 %
b1 '
b1 $
#900
0(
0!
b10 %
b10 '
b10 $
#910
1(
1!
b11 %
b11 '
b11 $
#920
0(
0!
b100 %
b100 '
b100 $
#930
b101 %
b101 '
b101 $
#940
b110 %
b110 '
b110 $
#950
b111 %
b111 '
b111 $
#960
b0 %
b0 '
b1100 "
b1100 &
b1100 #
b0 $
#970
b1 %
b1 '
b1 $
#980
1(
1!
b10 %
b10 '
b10 $
#990
b11 %
b11 '
b11 $
#1000
0(
0!
b100 %
b100 '
b100 $
#1010
b101 %
b101 '
b101 $
#1020
b110 %
b110 '
b110 $
#1030
b111 %
b111 '
b111 $
#1040
1(
1!
b0 %
b0 '
b1101 "
b1101 &
b1101 #
b0 $
#1050
0(
0!
b1 %
b1 '
b1 $
#1060
1(
1!
b10 %
b10 '
b10 $
#1070
b11 %
b11 '
b11 $
#1080
0(
0!
b100 %
b100 '
b100 $
#1090
b101 %
b101 '
b101 $
#1100
b110 %
b110 '
b110 $
#1110
b111 %
b111 '
b111 $
#1120
b0 %
b0 '
b1110 "
b1110 &
b1110 #
b0 $
#1130
1(
1!
b1 %
b1 '
b1 $
#1140
b10 %
b10 '
b10 $
#1150
b11 %
b11 '
b11 $
#1160
0(
0!
b100 %
b100 '
b100 $
#1170
b101 %
b101 '
b101 $
#1180
b110 %
b110 '
b110 $
#1190
b111 %
b111 '
b111 $
#1200
1(
1!
b0 %
b0 '
b1111 "
b1111 &
b1111 #
b0 $
#1210
b1 %
b1 '
b1 $
#1220
b10 %
b10 '
b10 $
#1230
b11 %
b11 '
b11 $
#1240
0(
0!
b100 %
b100 '
b100 $
#1250
b101 %
b101 '
b101 $
#1260
b110 %
b110 '
b110 $
#1270
b111 %
b111 '
b111 $
#1280
b0 %
b0 '
b10000 "
b10000 &
b10000 #
b0 $
#1290
b1 %
b1 '
b1 $
#1300
b10 %
b10 '
b10 $
#1310
b11 %
b11 '
b11 $
#1320
1(
1!
b100 %
b100 '
b100 $
#1330
0(
0!
b101 %
b101 '
b101 $
#1340
b110 %
b110 '
b110 $
#1350
b111 %
b111 '
b111 $
#1360
1(
1!
b0 %
b0 '
b10001 "
b10001 &
b10001 #
b0 $
#1370
0(
0!
b1 %
b1 '
b1 $
#1380
b10 %
b10 '
b10 $
#1390
b11 %
b11 '
b11 $
#1400
1(
1!
b100 %
b100 '
b100 $
#1410
0(
0!
b101 %
b101 '
b101 $
#1420
b110 %
b110 '
b110 $
#1430
b111 %
b111 '
b111 $
#1440
b0 %
b0 '
b10010 "
b10010 &
b10010 #
b0 $
#1450
1(
1!
b1 %
b1 '
b1 $
#1460
0(
0!
b10 %
b10 '
b10 $
#1470
b11 %
b11 '
b11 $
#1480
1(
1!
b100 %
b100 '
b100 $
#1490
0(
0!
b101 %
b101 '
b101 $
#1500
b110 %
b110 '
b110 $
#1510
b111 %
b111 '
b111 $
#1520
1(
1!
b0 %
b0 '
b10011 "
b10011 &
b10011 #
b0 $
#1530
b1 %
b1 '
b1 $
#1540
0(
0!
b10 %
b10 '
b10 $
#1550
b11 %
b11 '
b11 $
#1560
1(
1!
b100 %
b100 '
b100 $
#1570
0(
0!
b101 %
b101 '
b101 $
#1580
b110 %
b110 '
b110 $
#1590
b111 %
b111 '
b111 $
#1600
b0 %
b0 '
b10100 "
b10100 &
b10100 #
b0 $
#1610
b1 %
b1 '
b1 $
#1620
1(
1!
b10 %
b10 '
b10 $
#1630
0(
0!
b11 %
b11 '
b11 $
#1640
1(
1!
b100 %
b100 '
b100 $
#1650
0(
0!
b101 %
b101 '
b101 $
#1660
b110 %
b110 '
b110 $
#1670
b111 %
b111 '
b111 $
#1680
1(
1!
b0 %
b0 '
b10101 "
b10101 &
b10101 #
b0 $
#1690
0(
0!
b1 %
b1 '
b1 $
#1700
1(
1!
b10 %
b10 '
b10 $
#1710
0(
0!
b11 %
b11 '
b11 $
#1720
1(
1!
b100 %
b100 '
b100 $
#1730
0(
0!
b101 %
b101 '
b101 $
#1740
b110 %
b110 '
b110 $
#1750
b111 %
b111 '
b111 $
#1760
b0 %
b0 '
b10110 "
b10110 &
b10110 #
b0 $
#1770
1(
1!
b1 %
b1 '
b1 $
#1780
b10 %
b10 '
b10 $
#1790
0(
0!
b11 %
b11 '
b11 $
#1800
1(
1!
b100 %
b100 '
b100 $
#1810
0(
0!
b101 %
b101 '
b101 $
#1820
b110 %
b110 '
b110 $
#1830
b111 %
b111 '
b111 $
#1840
1(
1!
b0 %
b0 '
b10111 "
b10111 &
b10111 #
b0 $
#1850
b1 %
b1 '
b1 $
#1860
b10 %
b10 '
b10 $
#1870
0(
0!
b11 %
b11 '
b11 $
#1880
1(
1!
b100 %
b100 '
b100 $
#1890
0(
0!
b101 %
b101 '
b101 $
#1900
b110 %
b110 '
b110 $
#1910
b111 %
b111 '
b111 $
#1920
b0 %
b0 '
b11000 "
b11000 &
b11000 #
b0 $
#1930
b1 %
b1 '
b1 $
#1940
b10 %
b10 '
b10 $
#1950
1(
1!
b11 %
b11 '
b11 $
#1960
b100 %
b100 '
b100 $
#1970
0(
0!
b101 %
b101 '
b101 $
#1980
b110 %
b110 '
b110 $
#1990
b111 %
b111 '
b111 $
#2000
1(
1!
b0 %
b0 '
b11001 "
b11001 &
b11001 #
b0 $
#2010
0(
0!
b1 %
b1 '
b1 $
#2020
b10 %
b10 '
b10 $
#2030
1(
1!
b11 %
b11 '
b11 $
#2040
b100 %
b100 '
b100 $
#2050
0(
0!
b101 %
b101 '
b101 $
#2060
b110 %
b110 '
b110 $
#2070
b111 %
b111 '
b111 $
#2080
b0 %
b0 '
b11010 "
b11010 &
b11010 #
b0 $
#2090
1(
1!
b1 %
b1 '
b1 $
#2100
0(
0!
b10 %
b10 '
b10 $
#2110
1(
1!
b11 %
b11 '
b11 $
#2120
b100 %
b100 '
b100 $
#2130
0(
0!
b101 %
b101 '
b101 $
#2140
b110 %
b110 '
b110 $
#2150
b111 %
b111 '
b111 $
#2160
1(
1!
b0 %
b0 '
b11011 "
b11011 &
b11011 #
b0 $
#2170
b1 %
b1 '
b1 $
#2180
0(
0!
b10 %
b10 '
b10 $
#2190
1(
1!
b11 %
b11 '
b11 $
#2200
b100 %
b100 '
b100 $
#2210
0(
0!
b101 %
b101 '
b101 $
#2220
b110 %
b110 '
b110 $
#2230
b111 %
b111 '
b111 $
#2240
b0 %
b0 '
b11100 "
b11100 &
b11100 #
b0 $
#2250
b1 %
b1 '
b1 $
#2260
1(
1!
b10 %
b10 '
b10 $
#2270
b11 %
b11 '
b11 $
#2280
b100 %
b100 '
b100 $
#2290
0(
0!
b101 %
b101 '
b101 $
#2300
b110 %
b110 '
b110 $
#2310
b111 %
b111 '
b111 $
#2320
1(
1!
b0 %
b0 '
b11101 "
b11101 &
b11101 #
b0 $
#2330
0(
0!
b1 %
b1 '
b1 $
#2340
1(
1!
b10 %
b10 '
b10 $
#2350
b11 %
b11 '
b11 $
#2360
b100 %
b100 '
b100 $
#2370
0(
0!
b101 %
b101 '
b101 $
#2380
b110 %
b110 '
b110 $
#2390
b111 %
b111 '
b111 $
#2400
b0 %
b0 '
b11110 "
b11110 &
b11110 #
b0 $
#2410
1(
1!
b1 %
b1 '
b1 $
#2420
b10 %
b10 '
b10 $
#2430
b11 %
b11 '
b11 $
#2440
b100 %
b100 '
b100 $
#2450
0(
0!
b101 %
b101 '
b101 $
#2460
b110 %
b110 '
b110 $
#2470
b111 %
b111 '
b111 $
#2480
1(
1!
b0 %
b0 '
b11111 "
b11111 &
b11111 #
b0 $
#2490
b1 %
b1 '
b1 $
#2500
b10 %
b10 '
b10 $
#2510
b11 %
b11 '
b11 $
#2520
b100 %
b100 '
b100 $
#2530
0(
0!
b101 %
b101 '
b101 $
#2540
b110 %
b110 '
b110 $
#2550
b111 %
b111 '
b111 $
#2560
b0 %
b0 '
b100000 "
b100000 &
b100000 #
b0 $
#2570
b1 %
b1 '
b1 $
#2580
b10 %
b10 '
b10 $
#2590
b11 %
b11 '
b11 $
#2600
b100 %
b100 '
b100 $
#2610
1(
1!
b101 %
b101 '
b101 $
#2620
0(
0!
b110 %
b110 '
b110 $
#2630
b111 %
b111 '
b111 $
#2640
1(
1!
b0 %
b0 '
b100001 "
b100001 &
b100001 #
b0 $
#2650
0(
0!
b1 %
b1 '
b1 $
#2660
b10 %
b10 '
b10 $
#2670
b11 %
b11 '
b11 $
#2680
b100 %
b100 '
b100 $
#2690
1(
1!
b101 %
b101 '
b101 $
#2700
0(
0!
b110 %
b110 '
b110 $
#2710
b111 %
b111 '
b111 $
#2720
b0 %
b0 '
b100010 "
b100010 &
b100010 #
b0 $
#2730
1(
1!
b1 %
b1 '
b1 $
#2740
0(
0!
b10 %
b10 '
b10 $
#2750
b11 %
b11 '
b11 $
#2760
b100 %
b100 '
b100 $
#2770
1(
1!
b101 %
b101 '
b101 $
#2780
0(
0!
b110 %
b110 '
b110 $
#2790
b111 %
b111 '
b111 $
#2800
1(
1!
b0 %
b0 '
b100011 "
b100011 &
b100011 #
b0 $
#2810
b1 %
b1 '
b1 $
#2820
0(
0!
b10 %
b10 '
b10 $
#2830
b11 %
b11 '
b11 $
#2840
b100 %
b100 '
b100 $
#2850
1(
1!
b101 %
b101 '
b101 $
#2860
0(
0!
b110 %
b110 '
b110 $
#2870
b111 %
b111 '
b111 $
#2880
b0 %
b0 '
b100100 "
b100100 &
b100100 #
b0 $
#2890
b1 %
b1 '
b1 $
#2900
1(
1!
b10 %
b10 '
b10 $
#2910
0(
0!
b11 %
b11 '
b11 $
#2920
b100 %
b100 '
b100 $
#2930
1(
1!
b101 %
b101 '
b101 $
#2940
0(
0!
b110 %
b110 '
b110 $
#2950
b111 %
b111 '
b111 $
#2960
1(
1!
b0 %
b0 '
b100101 "
b100101 &
b100101 #
b0 $
#2970
0(
0!
b1 %
b1 '
b1 $
#2980
1(
1!
b10 %
b10 '
b10 $
#2990
0(
0!
b11 %
b11 '
b11 $
#3000
b100 %
b100 '
b100 $
#3010
1(
1!
b101 %
b101 '
b101 $
#3020
0(
0!
b110 %
b110 '
b110 $
#3030
b111 %
b111 '
b111 $
#3040
b0 %
b0 '
b100110 "
b100110 &
b100110 #
b0 $
#3050
1(
1!
b1 %
b1 '
b1 $
#3060
b10 %
b10 '
b10 $
#3070
0(
0!
b11 %
b11 '
b11 $
#3080
b100 %
b100 '
b100 $
#3090
1(
1!
b101 %
b101 '
b101 $
#3100
0(
0!
b110 %
b110 '
b110 $
#3110
b111 %
b111 '
b111 $
#3120
1(
1!
b0 %
b0 '
b100111 "
b100111 &
b100111 #
b0 $
#3130
b1 %
b1 '
b1 $
#3140
b10 %
b10 '
b10 $
#3150
0(
0!
b11 %
b11 '
b11 $
#3160
b100 %
b100 '
b100 $
#3170
1(
1!
b101 %
b101 '
b101 $
#3180
0(
0!
b110 %
b110 '
b110 $
#3190
b111 %
b111 '
b111 $
#3200
b0 %
b0 '
b101000 "
b101000 &
b101000 #
b0 $
#3210
b1 %
b1 '
b1 $
#3220
b10 %
b10 '
b10 $
#3230
1(
1!
b11 %
b11 '
b11 $
#3240
0(
0!
b100 %
b100 '
b100 $
#3250
1(
1!
b101 %
b101 '
b101 $
#3260
0(
0!
b110 %
b110 '
b110 $
#3270
b111 %
b111 '
b111 $
#3280
1(
1!
b0 %
b0 '
b101001 "
b101001 &
b101001 #
b0 $
#3290
0(
0!
b1 %
b1 '
b1 $
#3300
b10 %
b10 '
b10 $
#3310
1(
1!
b11 %
b11 '
b11 $
#3320
0(
0!
b100 %
b100 '
b100 $
#3330
1(
1!
b101 %
b101 '
b101 $
#3340
0(
0!
b110 %
b110 '
b110 $
#3350
b111 %
b111 '
b111 $
#3360
b0 %
b0 '
b101010 "
b101010 &
b101010 #
b0 $
#3370
1(
1!
b1 %
b1 '
b1 $
#3380
0(
0!
b10 %
b10 '
b10 $
#3390
1(
1!
b11 %
b11 '
b11 $
#3400
0(
0!
b100 %
b100 '
b100 $
#3410
1(
1!
b101 %
b101 '
b101 $
#3420
0(
0!
b110 %
b110 '
b110 $
#3430
b111 %
b111 '
b111 $
#3440
1(
1!
b0 %
b0 '
b101011 "
b101011 &
b101011 #
b0 $
#3450
b1 %
b1 '
b1 $
#3460
0(
0!
b10 %
b10 '
b10 $
#3470
1(
1!
b11 %
b11 '
b11 $
#3480
0(
0!
b100 %
b100 '
b100 $
#3490
1(
1!
b101 %
b101 '
b101 $
#3500
0(
0!
b110 %
b110 '
b110 $
#3510
b111 %
b111 '
b111 $
#3520
b0 %
b0 '
b101100 "
b101100 &
b101100 #
b0 $
#3530
b1 %
b1 '
b1 $
#3540
1(
1!
b10 %
b10 '
b10 $
#3550
b11 %
b11 '
b11 $
#3560
0(
0!
b100 %
b100 '
b100 $
#3570
1(
1!
b101 %
b101 '
b101 $
#3580
0(
0!
b110 %
b110 '
b110 $
#3590
b111 %
b111 '
b111 $
#3600
1(
1!
b0 %
b0 '
b101101 "
b101101 &
b101101 #
b0 $
#3610
0(
0!
b1 %
b1 '
b1 $
#3620
1(
1!
b10 %
b10 '
b10 $
#3630
b11 %
b11 '
b11 $
#3640
0(
0!
b100 %
b100 '
b100 $
#3650
1(
1!
b101 %
b101 '
b101 $
#3660
0(
0!
b110 %
b110 '
b110 $
#3670
b111 %
b111 '
b111 $
#3680
b0 %
b0 '
b101110 "
b101110 &
b101110 #
b0 $
#3690
1(
1!
b1 %
b1 '
b1 $
#3700
b10 %
b10 '
b10 $
#3710
b11 %
b11 '
b11 $
#3720
0(
0!
b100 %
b100 '
b100 $
#3730
1(
1!
b101 %
b101 '
b101 $
#3740
0(
0!
b110 %
b110 '
b110 $
#3750
b111 %
b111 '
b111 $
#3760
1(
1!
b0 %
b0 '
b101111 "
b101111 &
b101111 #
b0 $
#3770
b1 %
b1 '
b1 $
#3780
b10 %
b10 '
b10 $
#3790
b11 %
b11 '
b11 $
#3800
0(
0!
b100 %
b100 '
b100 $
#3810
1(
1!
b101 %
b101 '
b101 $
#3820
0(
0!
b110 %
b110 '
b110 $
#3830
b111 %
b111 '
b111 $
#3840
b0 %
b0 '
b110000 "
b110000 &
b110000 #
b0 $
#3850
b1 %
b1 '
b1 $
#3860
b10 %
b10 '
b10 $
#3870
b11 %
b11 '
b11 $
#3880
1(
1!
b100 %
b100 '
b100 $
#3890
b101 %
b101 '
b101 $
#3900
0(
0!
b110 %
b110 '
b110 $
#3910
b111 %
b111 '
b111 $
#3920
1(
1!
b0 %
b0 '
b110001 "
b110001 &
b110001 #
b0 $
#3930
0(
0!
b1 %
b1 '
b1 $
#3940
b10 %
b10 '
b10 $
#3950
b11 %
b11 '
b11 $
#3960
1(
1!
b100 %
b100 '
b100 $
#3970
b101 %
b101 '
b101 $
#3980
0(
0!
b110 %
b110 '
b110 $
#3990
b111 %
b111 '
b111 $
#4000
b0 %
b0 '
b110010 "
b110010 &
b110010 #
b0 $
#4010
1(
1!
b1 %
b1 '
b1 $
#4020
0(
0!
b10 %
b10 '
b10 $
#4030
b11 %
b11 '
b11 $
#4040
1(
1!
b100 %
b100 '
b100 $
#4050
b101 %
b101 '
b101 $
#4060
0(
0!
b110 %
b110 '
b110 $
#4070
b111 %
b111 '
b111 $
#4080
1(
1!
b0 %
b0 '
b110011 "
b110011 &
b110011 #
b0 $
#4090
b1 %
b1 '
b1 $
#4100
0(
0!
b10 %
b10 '
b10 $
#4110
b11 %
b11 '
b11 $
#4120
1(
1!
b100 %
b100 '
b100 $
#4130
b101 %
b101 '
b101 $
#4140
0(
0!
b110 %
b110 '
b110 $
#4150
b111 %
b111 '
b111 $
#4160
b0 %
b0 '
b110100 "
b110100 &
b110100 #
b0 $
#4170
b1 %
b1 '
b1 $
#4180
1(
1!
b10 %
b10 '
b10 $
#4190
0(
0!
b11 %
b11 '
b11 $
#4200
1(
1!
b100 %
b100 '
b100 $
#4210
b101 %
b101 '
b101 $
#4220
0(
0!
b110 %
b110 '
b110 $
#4230
b111 %
b111 '
b111 $
#4240
1(
1!
b0 %
b0 '
b110101 "
b110101 &
b110101 #
b0 $
#4250
0(
0!
b1 %
b1 '
b1 $
#4260
1(
1!
b10 %
b10 '
b10 $
#4270
0(
0!
b11 %
b11 '
b11 $
#4280
1(
1!
b100 %
b100 '
b100 $
#4290
b101 %
b101 '
b101 $
#4300
0(
0!
b110 %
b110 '
b110 $
#4310
b111 %
b111 '
b111 $
#4320
b0 %
b0 '
b110110 "
b110110 &
b110110 #
b0 $
#4330
1(
1!
b1 %
b1 '
b1 $
#4340
b10 %
b10 '
b10 $
#4350
0(
0!
b11 %
b11 '
b11 $
#4360
1(
1!
b100 %
b100 '
b100 $
#4370
b101 %
b101 '
b101 $
#4380
0(
0!
b110 %
b110 '
b110 $
#4390
b111 %
b111 '
b111 $
#4400
1(
1!
b0 %
b0 '
b110111 "
b110111 &
b110111 #
b0 $
#4410
b1 %
b1 '
b1 $
#4420
b10 %
b10 '
b10 $
#4430
0(
0!
b11 %
b11 '
b11 $
#4440
1(
1!
b100 %
b100 '
b100 $
#4450
b101 %
b101 '
b101 $
#4460
0(
0!
b110 %
b110 '
b110 $
#4470
b111 %
b111 '
b111 $
#4480
b0 %
b0 '
b111000 "
b111000 &
b111000 #
b0 $
#4490
b1 %
b1 '
b1 $
#4500
b10 %
b10 '
b10 $
#4510
1(
1!
b11 %
b11 '
b11 $
#4520
b100 %
b100 '
b100 $
#4530
b101 %
b101 '
b101 $
#4540
0(
0!
b110 %
b110 '
b110 $
#4550
b111 %
b111 '
b111 $
#4560
1(
1!
b0 %
b0 '
b111001 "
b111001 &
b111001 #
b0 $
#4570
0(
0!
b1 %
b1 '
b1 $
#4580
b10 %
b10 '
b10 $
#4590
1(
1!
b11 %
b11 '
b11 $
#4600
b100 %
b100 '
b100 $
#4610
b101 %
b101 '
b101 $
#4620
0(
0!
b110 %
b110 '
b110 $
#4630
b111 %
b111 '
b111 $
#4640
b0 %
b0 '
b111010 "
b111010 &
b111010 #
b0 $
#4650
1(
1!
b1 %
b1 '
b1 $
#4660
0(
0!
b10 %
b10 '
b10 $
#4670
1(
1!
b11 %
b11 '
b11 $
#4680
b100 %
b100 '
b100 $
#4690
b101 %
b101 '
b101 $
#4700
0(
0!
b110 %
b110 '
b110 $
#4710
b111 %
b111 '
b111 $
#4720
1(
1!
b0 %
b0 '
b111011 "
b111011 &
b111011 #
b0 $
#4730
b1 %
b1 '
b1 $
#4740
0(
0!
b10 %
b10 '
b10 $
#4750
1(
1!
b11 %
b11 '
b11 $
#4760
b100 %
b100 '
b100 $
#4770
b101 %
b101 '
b101 $
#4780
0(
0!
b110 %
b110 '
b110 $
#4790
b111 %
b111 '
b111 $
#4800
b0 %
b0 '
b111100 "
b111100 &
b111100 #
b0 $
#4810
b1 %
b1 '
b1 $
#4820
1(
1!
b10 %
b10 '
b10 $
#4830
b11 %
b11 '
b11 $
#4840
b100 %
b100 '
b100 $
#4850
b101 %
b101 '
b101 $
#4860
0(
0!
b110 %
b110 '
b110 $
#4870
b111 %
b111 '
b111 $
#4880
1(
1!
b0 %
b0 '
b111101 "
b111101 &
b111101 #
b0 $
#4890
0(
0!
b1 %
b1 '
b1 $
#4900
1(
1!
b10 %
b10 '
b10 $
#4910
b11 %
b11 '
b11 $
#4920
b100 %
b100 '
b100 $
#4930
b101 %
b101 '
b101 $
#4940
0(
0!
b110 %
b110 '
b110 $
#4950
b111 %
b111 '
b111 $
#4960
b0 %
b0 '
b111110 "
b111110 &
b111110 #
b0 $
#4970
1(
1!
b1 %
b1 '
b1 $
#4980
b10 %
b10 '
b10 $
#4990
b11 %
b11 '
b11 $
#5000
b100 %
b100 '
b100 $
#5010
b101 %
b101 '
b101 $
#5020
0(
0!
b110 %
b110 '
b110 $
#5030
b111 %
b111 '
b111 $
#5040
1(
1!
b0 %
b0 '
b111111 "
b111111 &
b111111 #
b0 $
#5050
b1 %
b1 '
b1 $
#5060
b10 %
b10 '
b10 $
#5070
b11 %
b11 '
b11 $
#5080
b100 %
b100 '
b100 $
#5090
b101 %
b101 '
b101 $
#5100
0(
0!
b110 %
b110 '
b110 $
#5110
b111 %
b111 '
b111 $
#5120
b0 %
b0 '
b1000000 "
b1000000 &
b1000000 #
b0 $
#5130
b1 %
b1 '
b1 $
#5140
b10 %
b10 '
b10 $
#5150
b11 %
b11 '
b11 $
#5160
b100 %
b100 '
b100 $
#5170
b101 %
b101 '
b101 $
#5180
1(
1!
b110 %
b110 '
b110 $
#5190
0(
0!
b111 %
b111 '
b111 $
#5200
1(
1!
b0 %
b0 '
b1000001 "
b1000001 &
b1000001 #
b0 $
#5210
0(
0!
b1 %
b1 '
b1 $
#5220
b10 %
b10 '
b10 $
#5230
b11 %
b11 '
b11 $
#5240
b100 %
b100 '
b100 $
#5250
b101 %
b101 '
b101 $
#5260
1(
1!
b110 %
b110 '
b110 $
#5270
0(
0!
b111 %
b111 '
b111 $
#5280
b0 %
b0 '
b1000010 "
b1000010 &
b1000010 #
b0 $
#5290
1(
1!
b1 %
b1 '
b1 $
#5300
0(
0!
b10 %
b10 '
b10 $
#5310
b11 %
b11 '
b11 $
#5320
b100 %
b100 '
b100 $
#5330
b101 %
b101 '
b101 $
#5340
1(
1!
b110 %
b110 '
b110 $
#5350
0(
0!
b111 %
b111 '
b111 $
#5360
1(
1!
b0 %
b0 '
b1000011 "
b1000011 &
b1000011 #
b0 $
#5370
b1 %
b1 '
b1 $
#5380
0(
0!
b10 %
b10 '
b10 $
#5390
b11 %
b11 '
b11 $
#5400
b100 %
b100 '
b100 $
#5410
b101 %
b101 '
b101 $
#5420
1(
1!
b110 %
b110 '
b110 $
#5430
0(
0!
b111 %
b111 '
b111 $
#5440
b0 %
b0 '
b1000100 "
b1000100 &
b1000100 #
b0 $
#5450
b1 %
b1 '
b1 $
#5460
1(
1!
b10 %
b10 '
b10 $
#5470
0(
0!
b11 %
b11 '
b11 $
#5480
b100 %
b100 '
b100 $
#5490
b101 %
b101 '
b101 $
#5500
1(
1!
b110 %
b110 '
b110 $
#5510
0(
0!
b111 %
b111 '
b111 $
#5520
1(
1!
b0 %
b0 '
b1000101 "
b1000101 &
b1000101 #
b0 $
#5530
0(
0!
b1 %
b1 '
b1 $
#5540
1(
1!
b10 %
b10 '
b10 $
#5550
0(
0!
b11 %
b11 '
b11 $
#5560
b100 %
b100 '
b100 $
#5570
b101 %
b101 '
b101 $
#5580
1(
1!
b110 %
b110 '
b110 $
#5590
0(
0!
b111 %
b111 '
b111 $
#5600
b0 %
b0 '
b1000110 "
b1000110 &
b1000110 #
b0 $
#5610
1(
1!
b1 %
b1 '
b1 $
#5620
b10 %
b10 '
b10 $
#5630
0(
0!
b11 %
b11 '
b11 $
#5640
b100 %
b100 '
b100 $
#5650
b101 %
b101 '
b101 $
#5660
1(
1!
b110 %
b110 '
b110 $
#5670
0(
0!
b111 %
b111 '
b111 $
#5680
1(
1!
b0 %
b0 '
b1000111 "
b1000111 &
b1000111 #
b0 $
#5690
b1 %
b1 '
b1 $
#5700
b10 %
b10 '
b10 $
#5710
0(
0!
b11 %
b11 '
b11 $
#5720
b100 %
b100 '
b100 $
#5730
b101 %
b101 '
b101 $
#5740
1(
1!
b110 %
b110 '
b110 $
#5750
0(
0!
b111 %
b111 '
b111 $
#5760
b0 %
b0 '
b1001000 "
b1001000 &
b1001000 #
b0 $
#5770
b1 %
b1 '
b1 $
#5780
b10 %
b10 '
b10 $
#5790
1(
1!
b11 %
b11 '
b11 $
#5800
0(
0!
b100 %
b100 '
b100 $
#5810
b101 %
b101 '
b101 $
#5820
1(
1!
b110 %
b110 '
b110 $
#5830
0(
0!
b111 %
b111 '
b111 $
#5840
1(
1!
b0 %
b0 '
b1001001 "
b1001001 &
b1001001 #
b0 $
#5850
0(
0!
b1 %
b1 '
b1 $
#5860
b10 %
b10 '
b10 $
#5870
1(
1!
b11 %
b11 '
b11 $
#5880
0(
0!
b100 %
b100 '
b100 $
#5890
b101 %
b101 '
b101 $
#5900
1(
1!
b110 %
b110 '
b110 $
#5910
0(
0!
b111 %
b111 '
b111 $
#5920
b0 %
b0 '
b1001010 "
b1001010 &
b1001010 #
b0 $
#5930
1(
1!
b1 %
b1 '
b1 $
#5940
0(
0!
b10 %
b10 '
b10 $
#5950
1(
1!
b11 %
b11 '
b11 $
#5960
0(
0!
b100 %
b100 '
b100 $
#5970
b101 %
b101 '
b101 $
