01_combinational_circuits/03_subtractors/03_fs_using_hs/fs_hs.v
module fs_hs(a, b, bin, diff, bout);
    input a, b, bin;
    output diff, bout;
    wire w1, w2, w3;

    hs h1(.a(a), .b(b), .d(w1), .bout(w2));
    hs h2(.a(w1), .b(bin), .d(diff), .bout(w3));

    assign bout = w2 | w3;

endmodule

module hs (a, b, d, bout);
    input a, b;
    output d, bout;
    assign d = a ^ b;
    assign bout = ~a & b;
endmodule

01_combinational_circuits/03_subtractors/03_fs_using_hs/fs_hs_tb.v
module fs_hs_tb;
reg a, b, bin;
wire d, bout;
fs_hs n1 (.a(a), .b(b), .bin(bin), .diff(d), .bout(bout));

initial begin
    $monitor("a = %b, b = %b, bin = %b, diff = %b, bout = %b", a, b,bin, d, bout);
    $dumpfile("fs_hs_tb.vcd");
    $dumpvars(0, fs_hs_tb);
end

initial begin
    a = 1'b0; b = 1'b0; bin = 1'b0; #10;
    a = 1'b0; b = 1'b0; bin = 1'b1; #10;
    a = 1'b0; b = 1'b1; bin = 1'b0; #10;
    a = 1'b0; b = 1'b1; bin = 1'b1; #10;
    a = 1'b1; b = 1'b0; bin = 1'b0; #10;
    a = 1'b1; b = 1'b0; bin = 1'b1; #10;
    a = 1'b1; b = 1'b1; bin = 1'b0; #10;
    a = 1'b1; b = 1'b1; bin = 1'b1; #10;
    $finish;
end
endmodule

01_combinational_circuits/03_subtractors/03_fs_using_hs/fs_hs_tb.vcd
$date
	Sun Apr 19 12:41:29 2026
$end
$version
	Icarus Verilog
$end
$timescale
	1s
$end
$scope module fs_hs_tb $end
$var wire 1 ! bout $end
$var wire 1 " d $end
$var reg 1 # a $end
$var reg 1 $ b $end
$var reg 1 % bin $end
$scope module n1 $end
$var wire 1 & a $end
$var wire 1 ' b $end
$var wire 1 ( bin $end
$var wire 1 ! bout $end
$var wire 1 " diff $end
$var wire 1 ) w1 $end
$var wire 1 * w2 $end
$var wire 1 + w3 $end
$scope module h1 $end
$var wire 1 & a $end
$var wire 1 ' b $end
$var wire 1 * bout $end
$var wire 1 ) d $end
$upscope $end
$scope module h2 $end
$var wire 1 ) a $end
$var wire 1 ( b $end
$var wire 1 + bout $end
$var wire 1 " d $end
$upscope $end
$upscope $end
$upscope $end
$enddefinitions $end
#0
$dumpvars
0+
0*
0)
0(
0'
0&
0%
0$
0#
0"
0!
$end
#10
1!
1"
1+
1%
1(
#20
0+
1)
1*
0%
0(
1$
1'
#30
0"
1%
1(
#40
0!
1"
0*
0%
0(
0$
0'
1#
1&
#50
0"
1%
1(
#60
0)
0%
0(
1$
1'
#70
1!
1"
1+
1%
1(
