01_combinational_circuits/02_adders/02_fulladder/fa.v
module fa (a, b, cin, sum, carry);
input a, b, cin;
output sum, carry;
assign sum = a ^ b ^ cin;
assign carry = (a & b) | (a & cin) | (b & cin);
endmodule

01_combinational_circuits/02_adders/02_fulladder/fa_tb.v
module fa_tb;
reg a, b, cin;
wire sum, carry;
fa n1 (.a(a), .b(b), .cin(cin), .sum(sum), .carry(carry));

initial begin
    $monitor("a = %b, b = %b, cin = %b,sum = %b, carry = %b", a, b,cin, sum, carry);
    $dumpfile("fa_tb.vcd");
    $dumpvars(0, fa_tb);
end

initial begin
    a = 1'b0; b = 1'b0; cin = 1'b0; #10;
    a = 1'b0; b = 1'b0; cin = 1'b1; #10;
    a = 1'b0; b = 1'b1; cin = 1'b0; #10;
    a = 1'b0; b = 1'b1; cin = 1'b1; #10;
    a = 1'b1; b = 1'b0; cin = 1'b0; #10;
    a = 1'b1; b = 1'b0; cin = 1'b1; #10;
    a = 1'b1; b = 1'b1; cin = 1'b0; #10;
    a = 1'b1; b = 1'b1; cin = 1'b1; #10;
    $finish;
end
endmodule

01_combinational_circuits/02_adders/02_fulladder/fa_tb.vcd
$date
	Tue Mar 31 23:53:22 2026
$end
$version
	Icarus Verilog
$end
$timescale
	1s
$end
$scope module fa_tb $end
$var wire 1 ! carry $end
$var wire 1 " sum $end
$var reg 1 # a $end
$var reg 1 $ b $end
$var reg 1 % cin $end
$scope module n1 $end
$var wire 1 & a $end
$var wire 1 ' b $end
$var wire 1 ! carry $end
$var wire 1 ( cin $end
$var wire 1 " sum $end
$upscope $end
$upscope $end
$enddefinitions $end
#0
$dumpvars
0(
0'
0&
0%
0$
0#
0"
0!
$end
#10
1"
1%
1(
#20
0%
0(
1$
1'
#30
1!
0"
1%
1(
#40
0!
1"
0%
0(
0$
0'
1#
1&
#50
1!
0"
1%
1(
#60
0%
0(
1$
1'
#70
1"
1%
1(
