01_combinational_circuits/02_adders/04_4-bit_RCA/rca.v
module rca (a, b, cin, sum, carry);
input [3:0] a, b;
input cin;
output [3:0] sum;
output carry;
wire c1, c2, c3;
fa f1 (a[0], b[0], cin, sum[0], c1);
fa f2 (a[1], b[1], c1, sum[1], c2);
fa f3 (a[2], b[2], c2, sum[2], c3);
fa f4 (a[3], b[3], c3, sum[3], carry);
endmodule

module fa (a, b, cin, sum, carry);
input a, b, cin;
output sum, carry;
assign sum = a ^ b ^ cin;
assign carry = (a & b) | (a & cin) | (b & cin);
endmodule

01_combinational_circuits/02_adders/04_4-bit_RCA/rca_tb.v
module rca_tb;
reg [3:0]a, b;
reg cin;
wire [3:0]sum;
wire carry;
rca n1 (.a(a), .b(b), .cin(cin), .sum(sum), .carry(carry));

initial begin
    $monitor("a = %b, b = %b, cin = %b,sum = %b, carry = %b", a, b,cin, sum, carry);
    $dumpfile("rca_tb.vcd");
    $dumpvars(0, rca_tb);
end

integer i, j, k;
initial begin
    for (i = 0; i < 16; i = i + 1) begin
        for (j = 0; j < 16; j = j + 1) begin
            for (k = 0; k < 2; k = k + 1) begin
                a = i;
                b = j;
                cin = k;
                #10;
            end
        end
    end
end
endmodule

01_combinational_circuits/02_adders/04_4-bit_RCA/rca_tb.vcd
$date
	Wed Apr 01 00:15:59 2026
$end
$version
	Icarus Verilog
$end
$timescale
	1s
$end
$scope module rca_tb $end
$var wire 1 ! carry $end
$var wire 4 " sum [3:0] $end
$var reg 4 # a [3:0] $end
$var reg 4 $ b [3:0] $end
$var reg 1 % cin $end
$var integer 32 & i [31:0] $end
$var integer 32 ' j [31:0] $end
$var integer 32 ( k [31:0] $end
$scope module n1 $end
$var wire 4 ) a [3:0] $end
$var wire 4 * b [3:0] $end
$var wire 1 + c1 $end
$var wire 1 , c2 $end
$var wire 1 - c3 $end
$var wire 1 ! carry $end
$var wire 1 . cin $end
$var wire 4 / sum [3:0] $end
$scope module f1 $end
$var wire 1 0 a $end
$var wire 1 1 b $end
$var wire 1 + carry $end
$var wire 1 . cin $end
$var wire 1 2 sum $end
$upscope $end
$scope module f2 $end
$var wire 1 3 a $end
$var wire 1 4 b $end
$var wire 1 , carry $end
$var wire 1 + cin $end
$var wire 1 5 sum $end
$upscope $end
$scope module f3 $end
$var wire 1 6 a $end
$var wire 1 7 b $end
$var wire 1 - carry $end
$var wire 1 , cin $end
$var wire 1 8 sum $end
$upscope $end
$scope module f4 $end
$var wire 1 9 a $end
$var wire 1 : b $end
$var wire 1 ! carry $end
$var wire 1 - cin $end
$var wire 1 ; sum $end
$upscope $end
$upscope $end
$upscope $end
$enddefinitions $end
#0
$dumpvars
0;
0:
09
08
07
06
05
04
03
02
01
00
b0 /
0.
0-
0,
0+
b0 *
b0 )
b0 (
b0 '
b0 &
0%
b0 $
b0 #
b0 "
0!
$end
#10
12
b1 "
b1 /
1%
1.
b1 (
#20
12
b1 "
b1 /
11
0%
0.
b1 $
b1 *
b1 '
b0 (
#30
15
1+
02
b10 "
b10 /
1%
1.
b1 (
#40
08
0,
0+
02
b10 "
b10 /
01
14
0%
0.
b10 $
b10 *
b10 '
b0 (
#50
12
b11 "
b11 /
1%
1.
b1 (
#60
12
b11 "
b11 /
11
0%
0.
b11 $
b11 *
b11 '
b0 (
#70
18
1,
05
1+
02
b100 "
b100 /
1%
1.
b1 (
#80
0;
0,
18
0-
0+
02
b100 "
b100 /
01
04
17
0%
0.
b100 $
b100 *
b100 '
b0 (
#90
12
b101 "
b101 /
1%
1.
b1 (
#100
12
b101 "
b101 /
11
0%
0.
b101 $
b101 *
b101 '
b0 (
#110
15
1+
02
b110 "
b110 /
1%
1.
b1 (
#120
0;
0-
18
0,
0+
02
b110 "
b110 /
01
14
0%
0.
b110 $
b110 *
b110 '
b0 (
#130
12
b111 "
b111 /
1%
1.
b1 (
#140
12
b111 "
b111 /
11
0%
0.
b111 $
b111 *
b111 '
b0 (
#150
1;
1-
08
1,
05
1+
02
b1000 "
b1000 /
1%
1.
b1 (
#160
0,
08
0-
1;
0!
0+
02
b1000 "
b1000 /
01
04
07
1:
0%
0.
b1000 $
b1000 *
b1000 '
b0 (
#170
12
b1001 "
b1001 /
1%
1.
b1 (
#180
12
b1001 "
b1001 /
11
0%
0.
b1001 $
b1001 *
b1001 '
b0 (
#190
15
1+
02
b1010 "
b1010 /
1%
1.
b1 (
#200
08
0,
0+
02
b1010 "
b1010 /
01
14
0%
0.
b1010 $
b1010 *
b1010 '
b0 (
#210
12
b1011 "
b1011 /
1%
1.
b1 (
#220
12
b1011 "
b1011 /
11
0%
0.
b1011 $
b1011 *
b1011 '
b0 (
#230
18
1,
05
1+
02
b1100 "
b1100 /
1%
1.
b1 (
#240
0!
1;
0,
18
0-
0+
02
b1100 "
b1100 /
01
04
17
0%
0.
b1100 $
b1100 *
b1100 '
b0 (
#250
12
b1101 "
b1101 /
1%
1.
b1 (
#260
12
b1101 "
b1101 /
11
0%
0.
b1101 $
b1101 *
b1101 '
b0 (
#270
15
1+
02
b1110 "
b1110 /
1%
1.
b1 (
#280
0!
1;
0-
18
0,
0+
02
b1110 "
b1110 /
01
14
0%
0.
b1110 $
b1110 *
b1110 '
b0 (
#290
12
b1111 "
b1111 /
1%
1.
b1 (
#300
12
b1111 "
b1111 /
11
0%
0.
b1111 $
b1111 *
b1111 '
b0 (
#310
1!
0;
1-
08
1,
05
1+
02
b0 "
b0 /
1%
1.
b1 (
#320
0,
08
0-
0;
0!
0+
12
b1 "
b1 /
01
04
07
0:
10
0%
0.
b0 $
b0 *
b1 #
b1 )
b1 &
b0 '
b0 (
#330
15
1+
02
b10 "
b10 /
1%
1.
b1 (
#340
02
b10 "
b10 /
11
0%
0.
b1 $
b1 *
b1 '
b0 (
#350
12
b11 "
b11 /
1%
1.
b1 (
#360
08
0+
15
0,
12
b11 "
b11 /
01
14
0%
0.
b10 $
b10 *
b10 '
b0 (
#370
18
1,
05
1+
02
b100 "
b100 /
1%
1.
b1 (
#380
02
b100 "
b100 /
11
0%
0.
b11 $
b11 *
b11 '
b0 (
#390
12
b101 "
b101 /
1%
1.
b1 (
#400
0;
0+
05
0,
18
0-
12
b101 "
b101 /
01
04
17
0%
0.
b100 $
b100 *
b100 '
b0 (
#410
15
1+
02
b110 "
b110 /
1%
1.
b1 (
#420
02
b110 "
b110 /
11
0%
0.
b101 $
b101 *
b101 '
b0 (
#430
12
b111 "
b111 /
1%
1.
b1 (
#440
0;
0-
18
0+
15
0,
12
b111 "
b111 /
01
14
0%
0.
b110 $
b110 *
b110 '
b0 (
#450
1;
1-
08
1,
05
1+
02
b1000 "
b1000 /
1%
1.
b1 (
#460
02
b1000 "
b1000 /
11
0%
0.
b111 $
b111 *
b111 '
b0 (
#470
12
b1001 "
b1001 /
1%
1.
b1 (
#480
0+
05
0,
08
0-
1;
0!
12
b1001 "
b1001 /
01
04
07
1:
0%
0.
b1000 $
b1000 *
b1000 '
b0 (
#490
15
1+
02
b1010 "
b1010 /
1%
1.
b1 (
#500
02
b1010 "
b1010 /
11
0%
0.
b1001 $
b1001 *
b1001 '
b0 (
#510
12
b1011 "
b1011 /
1%
1.
b1 (
#520
08
0+
15
0,
12
b1011 "
b1011 /
01
14
0%
0.
b1010 $
b1010 *
b1010 '
b0 (
#530
18
1,
05
1+
02
b1100 "
b1100 /
1%
1.
b1 (
#540
02
b1100 "
b1100 /
11
0%
0.
b1011 $
b1011 *
b1011 '
b0 (
#550
12
b1101 "
b1101 /
1%
1.
b1 (
#560
0!
1;
0+
05
0,
18
0-
12
b1101 "
b1101 /
01
04
17
0%
0.
b1100 $
b1100 *
b1100 '
b0 (
#570
15
1+
02
b1110 "
b1110 /
1%
1.
b1 (
#580
02
b1110 "
b1110 /
11
0%
0.
b1101 $
b1101 *
b1101 '
b0 (
#590
12
b1111 "
b1111 /
1%
1.
b1 (
#600
0!
1;
0-
18
0+
15
0,
12
b1111 "
b1111 /
01
14
0%
0.
b1110 $
b1110 *
b1110 '
b0 (
#610
1!
0;
1-
08
1,
05
1+
02
b0 "
b0 /
1%
1.
b1 (
#620
02
b0 "
b0 /
11
0%
0.
b1111 $
b1111 *
b1111 '
b0 (
#630
12
b1 "
b1 /
1%
1.
b1 (
#640
0,
15
0+
08
0-
0;
0!
02
b10 "
b10 /
01
04
07
0:
00
13
0%
0.
b0 $
b0 *
b10 #
b10 )
b10 &
b0 '
b0 (
#650
12
b11 "
b11 /
1%
1.
b1 (
#660
12
b11 "
b11 /
11
0%
0.
b1 $
b1 *
b1 '
b0 (
#670
18
1,
05
1+
02
b100 "
b100 /
1%
1.
b1 (
#680
0+
02
b100 "
b100 /
01
14
0%
0.
b10 $
b10 *
b10 '
b0 (
#690
12
b101 "
b101 /
1%
1.
b1 (
#700
12
b101 "
b101 /
11
0%
0.
b11 $
b11 *
b11 '
b0 (
#710
15
1+
02
b110 "
b110 /
1%
1.
b1 (
#720
0,
0;
18
0-
0+
02
b110 "
b110 /
01
04
17
0%
0.
b100 $
b100 *
b100 '
b0 (
#730
12
b111 "
b111 /
1%
1.
b1 (
#740
12
b111 "
b111 /
11
0%
0.
b101 $
b101 *
b101 '
b0 (
#750
1;
1-
08
1,
05
1+
02
b1000 "
b1000 /
1%
1.
b1 (
#760
0+
02
b1000 "
b1000 /
01
14
0%
0.
b110 $
b110 *
b110 '
b0 (
#770
12
b1001 "
b1001 /
1%
1.
b1 (
#780
12
b1001 "
b1001 /
11
0%
0.
b111 $
b111 *
b111 '
b0 (
#790
15
1+
02
b1010 "
b1010 /
1%
1.
b1 (
#800
0,
08
0-
1;
0!
0+
02
b1010 "
b1010 /
01
04
07
1:
0%
0.
b1000 $
b1000 *
b1000 '
b0 (
#810
12
b1011 "
b1011 /
1%
1.
b1 (
#820
12
b1011 "
b1011 /
11
0%
0.
b1001 $
b1001 *
b1001 '
b0 (
#830
18
1,
05
1+
02
b1100 "
b1100 /
1%
1.
b1 (
#840
0+
02
b1100 "
b1100 /
01
14
0%
0.
b1010 $
b1010 *
b1010 '
b0 (
#850
12
b1101 "
b1101 /
1%
1.
b1 (
#860
12
b1101 "
b1101 /
11
0%
0.
b1011 $
b1011 *
b1011 '
b0 (
#870
15
1+
02
b1110 "
b1110 /
1%
1.
b1 (
#880
0,
0!
1;
18
0-
0+
02
b1110 "
b1110 /
01
04
17
0%
0.
b1100 $
b1100 *
b1100 '
b0 (
#890
12
b1111 "
b1111 /
1%
1.
b1 (
#900
12
b1111 "
b1111 /
11
0%
0.
b1101 $
b1101 *
b1101 '
b0 (
#910
1!
0;
1-
08
1,
05
1+
02
b0 "
b0 /
1%
1.
b1 (
#920
0+
02
b0 "
b0 /
01
14
0%
0.
b1110 $
b1110 *
b1110 '
b0 (
#930
12
b1 "
b1 /
1%
1.
b1 (
#940
12
b1 "
b1 /
11
0%
0.
b1111 $
b1111 *
b1111 '
b0 (
#950
15
1+
02
b10 "
b10 /
1%
1.
b1 (
#960
0,
08
0-
0;
0!
0+
12
b11 "
b11 /
01
04
07
0:
10
0%
0.
b0 $
b0 *
b11 #
b11 )
b11 &
b0 '
b0 (
#970
18
1,
05
1+
02
b100 "
b100 /
1%
1.
b1 (
#980
02
b100 "
b100 /
11
0%
0.
b1 $
b1 *
b1 '
b0 (
#990
12
b101 "
b101 /
1%
1.
b1 (
#1000
0+
05
12
b101 "
b101 /
01
14
0%
0.
b10 $
b10 *
b10 '
b0 (
#1010
15
1+
02
b110 "
b110 /
1%
1.
b1 (
#1020
02
b110 "
b110 /
11
0%
0.
b11 $
b11 *
b11 '
b0 (
#1030
12
b111 "
b111 /
1%
1.
b1 (
#1040
0,
0;
0+
15
18
0-
12
b111 "
b111 /
01
04
17
0%
0.
b100 $
b100 *
b100 '
b0 (
#1050
1;
1-
08
1,
05
1+
02
b1000 "
b1000 /
1%
1.
b1 (
#1060
02
b1000 "
b1000 /
11
0%
0.
b101 $
b101 *
b101 '
b0 (
#1070
12
b1001 "
b1001 /
1%
1.
b1 (
#1080
0+
05
12
b1001 "
b1001 /
01
14
0%
0.
b110 $
b110 *
b110 '
b0 (
#1090
15
1+
02
b1010 "
b1010 /
1%
1.
b1 (
#1100
02
b1010 "
b1010 /
11
0%
0.
b111 $
b111 *
b111 '
b0 (
#1110
12
b1011 "
b1011 /
1%
1.
b1 (
#1120
0,
0+
15
08
0-
1;
0!
12
b1011 "
b1011 /
01
04
07
1:
0%
0.
b1000 $
b1000 *
b1000 '
b0 (
#1130
18
1,
05
1+
02
b1100 "
b1100 /
1%
1.
b1 (
#1140
02
b1100 "
b1100 /
11
0%
0.
b1001 $
b1001 *
b1001 '
b0 (
#1150
12
b1101 "
b1101 /
1%
1.
b1 (
#1160
0+
05
12
b1101 "
b1101 /
01
14
0%
0.
b1010 $
b1010 *
b1010 '
b0 (
#1170
15
1+
02
b1110 "
b1110 /
1%
1.
b1 (
#1180
02
b1110 "
b1110 /
11
0%
0.
b1011 $
b1011 *
b1011 '
b0 (
#1190
12
b1111 "
b1111 /
1%
1.
b1 (
#1200
0,
0!
1;
0+
15
18
0-
12
b1111 "
b1111 /
01
04
17
0%
0.
b1100 $
b1100 *
b1100 '
b0 (
#1210
1!
0;
1-
08
1,
05
1+
02
b0 "
b0 /
1%
1.
b1 (
#1220
02
b0 "
b0 /
11
0%
0.
b1101 $
b1101 *
b1101 '
b0 (
#1230
12
b1 "
b1 /
1%
1.
b1 (
#1240
0+
05
12
b1 "
b1 /
01
14
0%
0.
b1110 $
b1110 *
b1110 '
b0 (
#1250
15
1+
02
b10 "
b10 /
1%
1.
b1 (
#1260
02
b10 "
b10 /
11
0%
0.
b1111 $
b1111 *
b1111 '
b0 (
#1270
12
b11 "
b11 /
1%
1.
b1 (
#1280
0-
05
18
0+
0,
0;
0!
02
b100 "
b100 /
01
04
07
0:
00
03
16
0%
0.
b0 $
b0 *
b100 #
b100 )
b100 &
b0 '
b0 (
#1290
12
b101 "
b101 /
1%
1.
b1 (
#1300
12
b101 "
b101 /
11
0%
0.
b1 $
b1 *
b1 '
b0 (
#1310
15
1+
02
b110 "
b110 /
1%
1.
b1 (
#1320
0;
0-
18
0,
0+
02
b110 "
b110 /
01
14
0%
0.
b10 $
b10 *
b10 '
b0 (
#1330
12
b111 "
b111 /
1%
1.
b1 (
#1340
12
b111 "
b111 /
11
0%
0.
b11 $
b11 *
b11 '
b0 (
#1350
1;
1-
08
1,
05
1+
02
b1000 "
b1000 /
1%
1.
b1 (
#1360
0,
08
0+
02
b1000 "
b1000 /
01
04
17
0%
0.
b100 $
b100 *
b100 '
b0 (
#1370
12
b1001 "
b1001 /
1%
1.
b1 (
#1380
12
b1001 "
b1001 /
11
0%
0.
b101 $
b101 *
b101 '
b0 (
#1390
15
1+
02
b1010 "
b1010 /
1%
1.
b1 (
#1400
08
0,
0+
02
b1010 "
b1010 /
01
14
0%
0.
b110 $
b110 *
b110 '
b0 (
#1410
12
b1011 "
b1011 /
1%
1.
b1 (
#1420
12
b1011 "
b1011 /
11
0%
0.
b111 $
b111 *
b111 '
b0 (
#1430
18
1,
05
1+
02
b1100 "
b1100 /
1%
1.
b1 (
#1440
0-
0,
18
1;
0!
0+
02
b1100 "
b1100 /
01
04
07
1:
0%
0.
b1000 $
b1000 *
b1000 '
b0 (
#1450
12
b1101 "
b1101 /
1%
1.
b1 (
#1460
12
b1101 "
b1101 /
11
0%
0.
b1001 $
b1001 *
b1001 '
b0 (
#1470
15
1+
02
b1110 "
b1110 /
1%
1.
b1 (
#1480
0!
1;
0-
18
0,
0+
02
b1110 "
b1110 /
01
14
0%
0.
b1010 $
b1010 *
b1010 '
b0 (
#1490
12
b1111 "
b1111 /
1%
1.
b1 (
#1500
12
b1111 "
b1111 /
11
0%
0.
b1011 $
b1011 *
b1011 '
b0 (
#1510
1!
0;
1-
08
1,
05
1+
02
b0 "
b0 /
1%
1.
b1 (
#1520
0,
08
0+
02
b0 "
b0 /
01
04
17
0%
0.
b1100 $
b1100 *
b1100 '
b0 (
#1530
12
b1 "
b1 /
1%
1.
b1 (
#1540
12
b1 "
b1 /
11
0%
0.
b1101 $
b1101 *
b1101 '
b0 (
#1550
15
1+
02
b10 "
b10 /
1%
1.
b1 (
#1560
08
0,
0+
02
b10 "
b10 /
01
14
0%
0.
b1110 $
b1110 *
b1110 '
b0 (
#1570
12
b11 "
b11 /
1%
1.
b1 (
#1580
12
b11 "
b11 /
11
0%
0.
b1111 $
b1111 *
b1111 '
b0 (
#1590
18
1,
05
1+
02
b100 "
b100 /
1%
1.
b1 (
#1600
0-
0,
18
0;
0!
0+
12
b101 "
b101 /
01
04
07
0:
10
0%
0.
b0 $
b0 *
b101 #
b101 )
b101 &
b0 '
b0 (
#1610
15
1+
02
b110 "
b110 /
1%
1.
b1 (
#1620
02
b110 "
b110 /
11
0%
0.
b1 $
b1 *
b1 '
b0 (
#1630
12
b111 "
b111 /
1%
1.
b1 (
#1640
0;
0-
18
0+
15
0,
12
b111 "
b111 /
01
14
0%
0.
b10 $
b10 *
b10 '
b0 (
#1650
1;
1-
08
1,
05
1+
02
b1000 "
b1000 /
1%
1.
b1 (
#1660
02
b1000 "
b1000 /
11
0%
0.
b11 $
b11 *
b11 '
b0 (
#1670
12
b1001 "
b1001 /
1%
1.
b1 (
#1680
0+
05
0,
08
12
b1001 "
b1001 /
01
04
17
0%
0.
b100 $
b100 *
b100 '
b0 (
#1690
15
1+
02
b1010 "
b1010 /
1%
1.
b1 (
#1700
02
b1010 "
b1010 /
11
0%
0.
b101 $
b101 *
b101 '
b0 (
#1710
12
b1011 "
b1011 /
1%
1.
b1 (
#1720
08
0+
15
0,
12
b1011 "
b1011 /
01
14
0%
0.
b110 $
b110 *
b110 '
b0 (
#1730
18
1,
05
1+
02
b1100 "
b1100 /
1%
1.
b1 (
#1740
02
b1100 "
b1100 /
11
0%
0.
b111 $
b111 *
b111 '
b0 (
#1750
12
b1101 "
b1101 /
1%
1.
b1 (
#1760
0-
0+
05
0,
18
1;
0!
12
b1101 "
b1101 /
01
04
07
1:
0%
0.
b1000 $
b1000 *
b1000 '
b0 (
#1770
15
1+
02
b1110 "
b1110 /
1%
1.
b1 (
#1780
02
b1110 "
b1110 /
11
0%
0.
b1001 $
b1001 *
b1001 '
b0 (
#1790
12
b1111 "
b1111 /
1%
1.
b1 (
#1800
0!
1;
0-
18
0+
15
0,
12
b1111 "
b1111 /
01
14
0%
0.
b1010 $
b1010 *
b1010 '
b0 (
#1810
1!
0;
1-
08
1,
05
1+
02
b0 "
b0 /
1%
1.
b1 (
#1820
02
b0 "
b0 /
11
0%
0.
b1011 $
b1011 *
b1011 '
b0 (
#1830
12
b1 "
b1 /
1%
1.
b1 (
#1840
0+
05
0,
08
12
b1 "
b1 /
01
04
17
0%
0.
b1100 $
b1100 *
b1100 '
b0 (
#1850
15
1+
02
b10 "
b10 /
1%
1.
b1 (
#1860
02
b10 "
b10 /
11
0%
0.
b1101 $
b1101 *
b1101 '
b0 (
#1870
12
b11 "
b11 /
1%
1.
b1 (
#1880
08
0+
15
0,
12
b11 "
b11 /
01
14
0%
0.
b1110 $
b1110 *
b1110 '
b0 (
#1890
18
1,
05
1+
02
b100 "
b100 /
1%
1.
b1 (
#1900
02
b100 "
b100 /
11
0%
0.
b1111 $
b1111 *
b1111 '
b0 (
#1910
12
b101 "
b101 /
1%
1.
b1 (
#1920
0-
0,
15
0+
18
0;
0!
02
b110 "
b110 /
01
04
07
0:
00
13
0%
0.
b0 $
b0 *
b110 #
b110 )
b110 &
b0 '
b0 (
#1930
12
b111 "
b111 /
1%
1.
b1 (
#1940
12
b111 "
b111 /
11
0%
0.
b1 $
b1 *
b1 '
b0 (
#1950
1;
1-
08
1,
05
1+
02
b1000 "
b1000 /
1%
1.
b1 (
#1960
0+
02
b1000 "
b1000 /
01
14
0%
0.
b10 $
b10 *
b10 '
b0 (
#1970
12
b1001 "
b1001 /
1%
1.
b1 (
#1980
12
b1001 "
b1001 /
11
0%
0.
b11 $
b11 *
b11 '
b0 (
#1990
15
1+
02
b1010 "
b1010 /
1%
1.
b1 (
#2000
0,
08
0+
02
b1010 "
b1010 /
01
04
17
0%
0.
b100 $
b100 *
b100 '
b0 (
#2010
12
b1011 "
b1011 /
1%
1.
b1 (
#2020
12
b1011 "
b1011 /
11
0%
0.
b101 $
b101 *
b101 '
b0 (
#2030
18
1,
05
1+
02
b1100 "
b1100 /
1%
1.
b1 (
#2040
0+
02
b1100 "
b1100 /
01
14
0%
0.
b110 $
b110 *
b110 '
b0 (
#2050
12
b1101 "
b1101 /
1%
1.
b1 (
#2060
12
b1101 "
b1101 /
11
0%
0.
b111 $
b111 *
b111 '
b0 (
#2070
15
1+
02
b1110 "
b1110 /
1%
1.
b1 (
#2080
0-
0,
18
1;
0!
0+
02
b1110 "
b1110 /
01
04
07
1:
0%
0.
b1000 $
b1000 *
b1000 '
b0 (
#2090
12
b1111 "
b1111 /
1%
1.
b1 (
#2100
12
b1111 "
b1111 /
11
0%
0.
b1001 $
b1001 *
b1001 '
b0 (
#2110
1!
0;
1-
08
1,
05
1+
02
b0 "
b0 /
1%
1.
b1 (
#2120
0+
02
b0 "
b0 /
01
14
0%
0.
b1010 $
b1010 *
b1010 '
b0 (
#2130
12
b1 "
b1 /
1%
1.
b1 (
#2140
12
b1 "
b1 /
11
0%
0.
b1011 $
b1011 *
b1011 '
b0 (
#2150
15
1+
02
b10 "
b10 /
1%
1.
b1 (
#2160
0,
08
0+
02
b10 "
b10 /
01
04
17
0%
0.
b1100 $
b1100 *
b1100 '
b0 (
#2170
12
b11 "
b11 /
1%
1.
b1 (
#2180
12
b11 "
b11 /
11
0%
0.
b1101 $
b1101 *
b1101 '
b0 (
#2190
18
1,
05
1+
02
b100 "
b100 /
1%
1.
b1 (
#2200
0+
02
b100 "
b100 /
01
14
0%
0.
b1110 $
b1110 *
b1110 '
b0 (
#2210
12
b101 "
b101 /
1%
1.
b1 (
#2220
12
b101 "
b101 /
11
0%
0.
b1111 $
b1111 *
b1111 '
b0 (
#2230
15
1+
02
b110 "
b110 /
1%
1.
b1 (
#2240
0-
0,
18
0;
0!
0+
12
b111 "
b111 /
01
04
07
0:
10
0%
0.
b0 $
b0 *
b111 #
b111 )
b111 &
b0 '
b0 (
#2250
1;
1-
08
1,
05
1+
02
b1000 "
b1000 /
1%
1.
b1 (
#2260
02
b1000 "
b1000 /
11
0%
0.
b1 $
b1 *
b1 '
b0 (
#2270
12
b1001 "
b1001 /
1%
1.
b1 (
#2280
0+
05
12
b1001 "
b1001 /
01
14
0%
0.
b10 $
b10 *
b10 '
b0 (
#2290
15
1+
02
b1010 "
b1010 /
1%
1.
b1 (
#2300
02
b1010 "
b1010 /
11
0%
0.
b11 $
b11 *
b11 '
b0 (
#2310
12
b1011 "
b1011 /
1%
1.
b1 (
#2320
0,
0+
15
08
12
b1011 "
b1011 /
01
04
17
0%
0.
b100 $
b100 *
b100 '
b0 (
#2330
18
1,
05
1+
02
b1100 "
b1100 /
1%
1.
b1 (
#2340
02
b1100 "
b1100 /
11
0%
0.
b101 $
b101 *
b101 '
b0 (
#2350
12
b1101 "
b1101 /
1%
1.
b1 (
#2360
0+
05
12
b1101 "
b1101 /
01
14
0%
0.
b110 $
b110 *
b110 '
b0 (
#2370
15
1+
02
b1110 "
b1110 /
1%
1.
b1 (
#2380
02
b1110 "
b1110 /
11
0%
0.
b111 $
b111 *
b111 '
b0 (
#2390
12
b1111 "
b1111 /
1%
1.
b1 (
#2400
0-
0,
0+
15
18
1;
0!
12
b1111 "
b1111 /
01
04
07
1:
0%
0.
b1000 $
b1000 *
b1000 '
b0 (
#2410
1!
0;
1-
08
1,
05
1+
02
b0 "
b0 /
1%
1.
b1 (
#2420
02
b0 "
b0 /
11
0%
0.
b1001 $
b1001 *
b1001 '
b0 (
#2430
12
b1 "
b1 /
1%
1.
b1 (
#2440
0+
05
12
b1 "
b1 /
01
14
0%
0.
b1010 $
b1010 *
b1010 '
b0 (
#2450
15
1+
02
b10 "
b10 /
1%
1.
b1 (
#2460
02
b10 "
b10 /
11
0%
0.
b1011 $
b1011 *
b1011 '
b0 (
#2470
12
b11 "
b11 /
1%
1.
b1 (
#2480
0,
0+
15
08
12
b11 "
b11 /
01
04
17
0%
0.
b1100 $
b1100 *
b1100 '
b0 (
#2490
18
1,
05
1+
02
b100 "
b100 /
1%
1.
b1 (
#2500
02
b100 "
b100 /
11
0%
0.
b1101 $
b1101 *
b1101 '
b0 (
#2510
12
b101 "
b101 /
1%
1.
b1 (
#2520
0+
05
12
b101 "
b101 /
01
14
0%
0.
b1110 $
b1110 *
b1110 '
b0 (
#2530
15
1+
02
b110 "
b110 /
1%
1.
b1 (
#2540
02
b110 "
b110 /
11
0%
0.
b1111 $
b1111 *
b1111 '
b0 (
#2550
12
b111 "
b111 /
1%
1.
b1 (
#2560
0!
05
08
1;
0+
0,
0-
02
b1000 "
b1000 /
01
04
07
0:
00
03
06
19
0%
0.
b0 $
b0 *
b1000 #
b1000 )
b1000 &
b0 '
b0 (
#2570
12
b1001 "
b1001 /
1%
1.
b1 (
#2580
12
b1001 "
b1001 /
11
0%
0.
b1 $
b1 *
b1 '
b0 (
#2590
15
1+
02
b1010 "
b1010 /
1%
1.
b1 (
#2600
08
0,
0+
02
b1010 "
b1010 /
01
14
0%
0.
b10 $
b10 *
b10 '
b0 (
#2610
12
b1011 "
b1011 /
1%
1.
b1 (
#2620
12
b1011 "
b1011 /
11
0%
0.
b11 $
b11 *
b11 '
b0 (
#2630
18
1,
05
1+
02
b1100 "
b1100 /
1%
1.
b1 (
#2640
0!
1;
0,
18
0-
0+
02
b1100 "
b1100 /
01
04
17
0%
0.
b100 $
b100 *
b100 '
b0 (
#2650
12
b1101 "
b1101 /
1%
1.
b1 (
#2660
12
b1101 "
b1101 /
11
0%
0.
b101 $
b101 *
b101 '
b0 (
#2670
15
1+
02
b1110 "
b1110 /
1%
1.
b1 (
#2680
0!
1;
0-
18
0,
0+
02
b1110 "
b1110 /
01
14
0%
0.
b110 $
b110 *
b110 '
b0 (
#2690
12
b1111 "
b1111 /
1%
1.
b1 (
#2700
12
b1111 "
b1111 /
11
0%
0.
b111 $
b111 *
b111 '
b0 (
#2710
1!
0;
1-
08
1,
05
1+
02
b0 "
b0 /
1%
1.
b1 (
#2720
0,
08
0-
0;
0+
02
b0 "
b0 /
01
04
07
1:
0%
0.
b1000 $
b1000 *
b1000 '
b0 (
#2730
12
b1 "
b1 /
1%
1.
b1 (
#2740
12
b1 "
b1 /
11
0%
0.
b1001 $
b1001 *
b1001 '
b0 (
#2750
15
1+
02
b10 "
b10 /
1%
1.
b1 (
#2760
08
0,
0+
02
b10 "
b10 /
01
14
0%
0.
b1010 $
b1010 *
b1010 '
b0 (
#2770
12
b11 "
b11 /
1%
1.
b1 (
#2780
12
b11 "
b11 /
11
0%
0.
b1011 $
b1011 *
b1011 '
b0 (
#2790
18
1,
05
1+
02
b100 "
b100 /
1%
1.
b1 (
#2800
0;
0,
18
0-
0+
02
b100 "
b100 /
01
04
17
0%
0.
b1100 $
b1100 *
b1100 '
b0 (
#2810
12
b101 "
b101 /
1%
1.
b1 (
#2820
12
b101 "
b101 /
11
0%
0.
b1101 $
b1101 *
b1101 '
b0 (
#2830
15
1+
02
b110 "
b110 /
1%
1.
b1 (
#2840
0;
0-
18
0,
0+
02
b110 "
b110 /
01
14
0%
0.
b1110 $
b1110 *
b1110 '
b0 (
#2850
12
b111 "
b111 /
1%
1.
b1 (
#2860
12
b111 "
b111 /
11
0%
0.
b1111 $
b1111 *
b1111 '
b0 (
#2870
1;
1-
08
1,
05
1+
02
b1000 "
b1000 /
1%
1.
b1 (
#2880
0!
0,
08
0-
1;
0+
12
b1001 "
b1001 /
01
04
07
0:
10
0%
0.
b0 $
b0 *
b1001 #
b1001 )
b1001 &
b0 '
b0 (
#2890
15
1+
02
b1010 "
b1010 /
1%
1.
b1 (
#2900
02
b1010 "
b1010 /
11
0%
0.
b1 $
b1 *
b1 '
b0 (
#2910
12
b1011 "
b1011 /
1%
1.
b1 (
#2920
08
0+
15
0,
12
b1011 "
b1011 /
01
14
0%
0.
b10 $
b10 *
b10 '
b0 (
#2930
18
1,
05
1+
02
b1100 "
b1100 /
1%
1.
b1 (
#2940
02
b1100 "
b1100 /
11
0%
0.
b11 $
b11 *
b11 '
b0 (
#2950
12
b1101 "
b1101 /
1%
1.
b1 (
#2960
0!
1;
0+
05
0,
18
0-
12
b1101 "
b1101 /
01
04
17
0%
0.
b100 $
b100 *
b100 '
b0 (
#2970
15
1+
02
b1110 "
b1110 /
1%
1.
b1 (
#2980
02
b1110 "
b1110 /
11
0%
0.
b101 $
b101 *
b101 '
b0 (
#2990
12
b1111 "
b1111 /
1%
1.
b1 (
#3000
0!
1;
0-
18
0+
15
0,
12
b1111 "
b1111 /
01
14
0%
0.
b110 $
b110 *
b110 '
b0 (
#3010
1!
0;
1-
08
1,
05
1+
02
b0 "
b0 /
1%
1.
b1 (
#3020
02
b0 "
b0 /
11
0%
0.
b111 $
b111 *
b111 '
b0 (
#3030
12
b1 "
b1 /
1%
1.
b1 (
#3040
0+
05
0,
08
0-
0;
12
b1 "
b1 /
01
04
07
1:
0%
0.
b1000 $
b1000 *
b1000 '
b0 (
#3050
15
1+
02
b10 "
b10 /
1%
1.
b1 (
#3060
02
b10 "
b10 /
11
0%
0.
b1001 $
b1001 *
b1001 '
b0 (
#3070
12
b11 "
b11 /
1%
1.
b1 (
#3080
08
0+
15
0,
12
b11 "
b11 /
01
14
0%
0.
b1010 $
b1010 *
b1010 '
b0 (
#3090
18
1,
05
1+
02
b100 "
b100 /
1%
1.
b1 (
