01_combinational_circuits/04_mux/10_kx1_mux/kx1_mux.v
module mux_Kx1 #(parameter K = 64)(i, sel, y);
    input  [K-1:0] i;
    input  [$clog2(K)-1:0] sel;
    output y;

    assign y = i[sel];

endmodule

01_combinational_circuits/04_mux/10_kx1_mux/kx1_mux_tb.v
module mux_Kx1_tb;
    parameter K = 64;
    reg [K-1:0] i;
    reg [5:0] sel;
    wire y;

    mux_Kx1 #(K) uut (
        .i(i),
        .sel(sel),
        .y(y)
);

    initial begin
        $dumpfile("mux_kx1.vcd");
        $dumpvars(0, mux_Kx1_tb);
        $monitor("time=%0t sel=%d y=%b", $time, sel, y);

        i = 64'hAAAAAAAAAAAAAAAA; sel = 0;  #10;
        sel = 1;  #10;
        sel = 2;  #10;
        sel = 3;  #10;

        i = 64'h5555555555555555; sel = 4;  #10;
        sel = 5;  #10;
        sel = 6;  #10;

        i = 64'hF0F0F0F0F0F0F0F0; sel = 10; #10;
        sel = 20; #10;
        sel = 30; #10;

        $finish;
    end

endmodule

01_combinational_circuits/04_mux/10_kx1_mux/mux_Kx1.vcd
$date
	Sat Apr 25 17:21:51 2026
$end
$version
	Icarus Verilog
$end
$timescale
	1s
$end
$scope module mux_Kx1_tb $end
$var wire 1 ! y $end
$var reg 64 " i [63:0] $end
$var reg 6 # sel [5:0] $end
$scope module uut $end
$var wire 64 $ i [63:0] $end
$var wire 6 % sel [5:0] $end
$var wire 1 ! y $end
$upscope $end
$upscope $end
$enddefinitions $end
#0
$dumpvars
b0 %
b1010101010101010101010101010101010101010101010101010101010101010 $
b0 #
b1010101010101010101010101010101010101010101010101010101010101010 "
0!
$end
#10
b1 #
b1 %
1!
#20
b10 #
b10 %
0!
#30
b11 #
b11 %
1!
#40
b100 #
b100 %
b101010101010101010101010101010101010101010101010101010101010101 "
b101010101010101010101010101010101010101010101010101010101010101 $
1!
#50
b101 #
b101 %
0!
#60
b110 #
b110 %
1!
#70
b1010 #
b1010 %
0!
b1111000011110000111100001111000011110000111100001111000011110000 "
b1111000011110000111100001111000011110000111100001111000011110000 $
#80
b10100 #
b10100 %
1!
#90
b11110 #
b11110 %
