01_combinational_circuits/04_mux/08_fa_using_mux/fa_using_mux.v
module fa_using_mux(a, b, cin, sum, cout);
    input a, b, cin;
    output sum, cout;

    mux_4x1 mux_sum(cin, ~cin, ~cin, cin, b, a, sum );
    mux_4x1 mux_cout(1'b0, cin, cin, 1'b1, b, a, cout);
endmodule
    

module mux_4x1 (a, b, c, d, s0, s1, y);
    input a, b, c, d, s0, s1;
    output y;

    assign y = (~s1 & ~s0 & a) | 
               (~s1 & s0 & b) | 
               (s1 & ~s0 & c) | 
               (s1 & s0 & d);
endmodule

01_combinational_circuits/04_mux/08_fa_using_mux/fa_using_mux_tb.v
module fa_using_mux_tb;
reg a, b, cin;
wire sum, carry;
fa_using_mux n1 (.a(a), .b(b), .cin(cin), .sum(sum), .cout(carry));

initial begin
    $monitor("a = %b, b = %b, cin = %b,sum = %b, carry = %b", a, b,cin, sum, carry);
    $dumpfile("fa_using_mux_tb.vcd");
    $dumpvars(0, fa_using_mux_tb);
end

initial begin
    a = 1'b0; b = 1'b0; cin = 1'b0; #10;
    a = 1'b0; b = 1'b0; cin = 1'b1; #10;
    a = 1'b0; b = 1'b1; cin = 1'b0; #10;
    a = 1'b0; b = 1'b1; cin = 1'b1; #10;
    a = 1'b1; b = 1'b0; cin = 1'b0; #10;
    a = 1'b1; b = 1'b0; cin = 1'b1; #10;
    a = 1'b1; b = 1'b1; cin = 1'b0; #10;
    a = 1'b1; b = 1'b1; cin = 1'b1; #10;
    $finish;
end
endmodule

01_combinational_circuits/04_mux/08_fa_using_mux/fa_using_mux_tb.vcd
$date
	Sat Apr 25 16:59:04 2026
$end
$version
	Icarus Verilog
$end
$timescale
	1s
$end
$scope module fa_using_mux_tb $end
$var wire 1 ! carry $end
$var wire 1 " sum $end
$var reg 1 # a $end
$var reg 1 $ b $end
$var reg 1 % cin $end
$scope module n1 $end
$var wire 1 & a $end
$var wire 1 ' b $end
$var wire 1 ( cin $end
$var wire 1 ! cout $end
$var wire 1 " sum $end
$scope module mux_sum $end
$var wire 1 ( a $end
$var wire 1 ) b $end
$var wire 1 * c $end
$var wire 1 ( d $end
$var wire 1 ' s0 $end
$var wire 1 & s1 $end
$var wire 1 " y $end
$upscope $end
$scope module mux_cout $end
$var wire 1 + a $end
$var wire 1 ( b $end
$var wire 1 ( c $end
$var wire 1 , d $end
$var wire 1 ' s0 $end
$var wire 1 & s1 $end
$var wire 1 ! y $end
$upscope $end
$upscope $end
$upscope $end
$enddefinitions $end
#0
$dumpvars
1,
0+
1*
1)
0(
0'
0&
0%
0$
0#
0"
0!
$end
#10
1"
0)
0*
1%
1(
#20
1)
1*
0%
0(
1$
1'
#30
0"
1!
0)
0*
1%
1(
#40
1"
0!
1)
1*
0%
0(
0$
0'
1#
1&
#50
0"
1!
0)
0*
1%
1(
#60
1)
1*
0%
0(
1$
1'
#70
1"
0)
0*
1%
1(
